[
  {
    "Id": "a92fd71c77a443c58727fb9a2d2cf001",
    "Name": "Super Brain Classic",
    "Maze": {
      "Level": 7,
      "StartRoom": 2,
      "EntryDoor": 0,
      "Path": "25152535303542422442211010111245254345452021101012030310134534433043015125201034043",
      "Stars": [
        "1",
        "45",
        "94",
        "126"
      ],
      "Traps": {
        "1": "115",
        "25": "00153242",
        "36": "244224",
        "113": "3315",
        "85": "2034015213",
        "39": "1",
        "63": "012543",
        "51": "22",
        "52": "55",
        "109": "33",
        "122": "0024",
        "123": "02",
        "118": "5131513",
        "110": "20",
        "101": "11044420",
        "69": "20",
        "42": "11135",
        "20": "51"
      }
    },
    "Author": "AI"
  },
  {
    "Id": "a92fd71c77a443c58727fb9a2d205001",
    "Name": "Easy 1",
    "Maze": {
      "Stars": [
        "27",
        "10"
      ],
      "Path": "3452510303035534431131204555152252443431312203340343",
      "Traps": {
        "26": "2413",
        "32": "32",
        "19": "204520230",
        "61": "32",
        "43": "0415",
        "2": "45214",
        "57": "05"
      },
      "StartRoom": 43,
      "Level": 5,
      "EntryDoor": 2
    }
  },
  {
    "Id": "a92fd71c77a443c58727fb9a2d205002",
    "Name": "Easy 2",
    "Maze": {
      "Stars": [
        "27",
        "18"
      ],
      "Path": "1130311124243521245445331111252000012545552",
      "Traps": {
        "34": "50",
        "11": "3502",
        "45": "251034530",
        "19": "024",
        "61": "0415",
        "17": "5500",
        "12": "0235",
        "59": "1441",
        "50": "5410",
        "18": "4411"
      },
      "StartRoom": 19,
      "Level": 5,
      "EntryDoor": 3
    }
  },
  {
    "Id": "a92fd71c77a443c58727fb9a2d205003",
    "Name": "Easy 3",
    "Maze": {
      "Stars": [
        "49",
        "57"
      ],
      "Path": "24253452242151000035543445452025113304343003",
      "Traps": {
        "1": "5014",
        "49": "14",
        "7": "5131131155454455311",
        "11": "5034"
      },
      "StartRoom": 11,
      "Level": 5,
      "EntryDoor": 1
    }
  },
  {
    "Id": "a92fd71c77a443c58727fb9a2d205004",
    "Name": "Easy 4",
    "Maze": {
      "Stars": [
        "9",
        "49"
      ],
      "Path": "331133530022130011551152553302433034531225520224522",
      "Traps": {
        "27": "23",
        "11": "41",
        "57": "135301023",
        "56": "5342413",
        "35": "555325",
        "26": "2413"
      },
      "StartRoom": 51,
      "Level": 5,
      "EntryDoor": 4
    }
  },
  {
    "Id": "a92fd71c77a443c58727fb9a2d205005",
    "Name": "Easy 5",
    "Maze": {
      "Stars": [
        "27",
        "47"
      ],
      "Path": "55554045400442421303453030211202543444210001113310",
      "Traps": {
        "7": "2332",
        "11": "41",
        "48": "41",
        "35": "45304440043114",
        "6": "2503",
        "41": "2503",
        "18": "4123"
      },
      "StartRoom": 35,
      "Level": 5,
      "EntryDoor": 1
    }
  },
  {
    "Id": "a92fd71c77a443c58727fb9a2d205006",
    "Name": "Easy 6",
    "Maze": {
      "Stars": [
        "33",
        "37"
      ],
      "Path": "511034201120222244225355104440103535533134453",
      "Traps": {
        "37": "40251511450",
        "24": "1504",
        "9": "2053",
        "17": "14",
        "43": "05",
        "6": "21",
        "15": "51312503",
        "57": "1111"
      },
      "StartRoom": 6,
      "Level": 5,
      "EntryDoor": 4
    }
  },
  {
    "Id": "a92fd71c77a443c58727fb9a2d205007",
    "Name": "Easy 7",
    "Maze": {
      "Stars": [
        "10",
        "31"
      ],
      "Path": "431134444354310401151511025330424315225512421543534330201524544",
      "Traps": {
        "44": "05",
        "50": "50",
        "28": "5140",
        "57": "1324",
        "27": "0145",
        "43": "305"
      },
      "StartRoom": 43,
      "Level": 5,
      "EntryDoor": 2
    }
  },
  {
    "Id": "a92fd71c77a443c58727fb9a2d205008",
    "Name": "Easy 8",
    "Maze": {
      "Stars": [
        "1",
        "19"
      ],
      "Path": "543152535404002531151122422200331254010",
      "Traps": {
        "46": "135400432221",
        "54": "1144",
        "57": "1015",
        "4": "5015",
        "56": "54",
        "18": "40354255222543443040405"
      },
      "StartRoom": 4,
      "Level": 5,
      "EntryDoor": 3
    }
  },
  {
    "Id": "a92fd71c77a443c58727fb9a2d205009",
    "Name": "Easy 9",
    "Maze": {
      "Stars": [
        "9",
        "53"
      ],
      "Path": "4540001344520211555454443131131335335451151042544",
      "Traps": {
        "7": "5032",
        "4": "12435451504",
        "61": "05",
        "12": "0235",
        "54": "4501",
        "36": "14",
        "2": "15"
      },
      "StartRoom": 43,
      "Level": 5,
      "EntryDoor": 1
    }
  },
  {
    "Id": "a92fd71c77a443c58727fb9a2d206001",
    "Name": "Hard 1",
    "Maze": {
      "Stars": [
        "28",
        "53",
        "73"
      ],
      "Path": "5202244254530130110042201045221510033524222022033340455525115510025544243452",
      "Traps": {
        "91": "41",
        "86": "30004542215140",
        "26": "5540125551504",
        "53": "05",
        "48": "14",
        "1": "5",
        "67": "05",
        "75": "3052",
        "88": "14"
      },
      "StartRoom": 1,
      "Level": 6,
      "EntryDoor": 3
    }
  },
  {
    "Id": "a92fd71c77a443c58727fb9a2d206002",
    "Name": "Hard 2",
    "Maze": {
      "Stars": [
        "55",
        "43",
        "85"
      ],
      "Path": "2020251545435540310400222001015215455453545201121030203102245201",
      "Traps": {
        "57": "2503",
        "91": "44",
        "2": "112",
        "85": "044120",
        "71": "2053",
        "77": "54540355304250",
        "41": "22020",
        "31": "5140"
      },
      "StartRoom": 2,
      "Level": 6,
      "EntryDoor": 3
    }
  },
  {
    "Id": "a92fd71c77a443c58727fb9a2d206003",
    "Name": "Hard 3",
    "Maze": {
      "Stars": [
        "45",
        "75",
        "9"
      ],
      "Path": "0345225533040004435215545545213112104035353444002015521524035433303103000",
      "Traps": {
        "19": "13530122253123",
        "4": "4451542513",
        "17": "54212503",
        "61": "313",
        "10": "5230"
      },
      "StartRoom": 61,
      "Level": 6,
      "EntryDoor": 2
    }
  },
  {
    "Id": "a92fd71c77a443c58727fb9a2d206004",
    "Name": "Hard 4",
    "Maze": {
      "Stars": [
        "59",
        "74",
        "3"
      ],
      "Path": "253353452553010222102520020224422535421043045545300200434045421544",
      "Traps": {
        "13": "5511333554534523",
        "52": "14",
        "89": "4411",
        "4": "1504",
        "79": "2143",
        "71": "1324",
        "51": "3502",
        "72": "00331",
        "41": "0235",
        "70": "32"
      },
      "StartRoom": 4,
      "Level": 6,
      "EntryDoor": 3
    }
  },
  {
    "Id": "a92fd71c77a443c58727fb9a2d206005",
    "Name": "Hard 5",
    "Maze": {
      "Stars": [
        "52",
        "70",
        "4"
      ],
      "Path": "445544435442115251102033535204442120211104043100251004513400404044225424433553043",
      "Traps": {
        "31": "240115",
        "4": "11504",
        "27": "3142",
        "18": "334455113125155544",
        "40": "25"
      },
      "StartRoom": 40,
      "Level": 6,
      "EntryDoor": 0
    }
  },
  {
    "Id": "a92fd71c77a443c58727fb9a2d206006",
    "Name": "Hard 6",
    "Maze": {
      "Stars": [
        "11",
        "23",
        "55"
      ],
      "Path": "31215421242113022003312010133404544301203122255354312221542540000153345101202",
      "Traps": {
        "52": "3",
        "55": "2233",
        "24": "024335254012211314431",
        "4": "4231",
        "56": "2503",
        "1": "1223431",
        "64": "2503",
        "43": "23",
        "75": "05",
        "18": "50"
      },
      "StartRoom": 52,
      "Level": 6,
      "EntryDoor": 5
    }
  },
  {
    "Id": "a92fd71c77a443c58727fb9a2d206007",
    "Name": "Hard 7",
    "Maze": {
      "Stars": [
        "74",
        "45",
        "61"
      ],
      "Path": "3100251021103344001344245200211015224355404424444303511310404001520100",
      "Traps": {
        "21": "5032",
        "3": "14",
        "70": "5410",
        "11": "0415",
        "79": "13250",
        "22": "23",
        "85": "0415",
        "44": "5435",
        "6": "5312523",
        "40": "2503",
        "88": "31511134321"
      },
      "StartRoom": 79,
      "Level": 6,
      "EntryDoor": 5
    }
  },
  {
    "Id": "a92fd71c77a443c58727fb9a2d206008",
    "Name": "Hard 8",
    "Maze": {
      "Stars": [
        "91",
        "58",
        "23"
      ],
      "Path": "21304351030212004431312104553525212120310310354035555201310302443111",
      "Traps": {
        "30": "245411133",
        "91": "30044214",
        "68": "0115554540043422535404002110523",
        "52": "1112"
      },
      "StartRoom": 52,
      "Level": 6,
      "EntryDoor": 4
    }
  },
  {
    "Id": "a92fd71c77a443c58727fb9a2d206009",
    "Name": "Hard 9",
    "Maze": {
      "Stars": [
        "46",
        "63",
        "24"
      ],
      "Path": "400203353430213345425554342533010400210452155311122025542454313104012403333100",
      "Traps": {
        "63": "2431522131210214",
        "83": "102004",
        "52": "3142",
        "55": "420325"
      },
      "StartRoom": 70,
      "Level": 6,
      "EntryDoor": 2
    }
  },
  {
    "Id": "a92fd71c77a443c58727fb9a2d207001",
    "Name": "Super 1",
    "Maze": {
      "Stars": [
        "21",
        "65",
        "1",
        "110"
      ],
      "Path": "1011224520110021225334252555354313403335454",
      "Traps": {
        "91": "2242454114",
        "60": "311310303532",
        "16": "2305",
        "11": "315101125342220122533500333",
        "84": "2421242114",
        "87": "2210331000444302132",
        "88": "4501"
      },
      "StartRoom": 35,
      "Level": 7,
      "EntryDoor": 3
    }
  },
  {
    "Id": "a92fd71c77a443c58727fb9a2d207002",
    "Name": "Super 2",
    "Maze": {
      "Stars": [
        "60",
        "106",
        "66",
        "16"
      ],
      "Path": "242154433044352225333345155224435220254",
      "Traps": {
        "99": "224243543015213",
        "89": "33453415",
        "53": "5131221203454252253530344035430040400103",
        "30": "3502",
        "95": "0415",
        "56": "4321",
        "15": "404444441",
        "70": "3335"
      },
      "StartRoom": 15,
      "Level": 7,
      "EntryDoor": 0
    }
  },
  {
    "Id": "a92fd71c77a443c58727fb9a2d207003",
    "Name": "Super 3",
    "Maze": {
      "Stars": [
        "5",
        "70",
        "76",
        "55"
      ],
      "Path": "52533044524542201115244442433552243333",
      "Traps": {
        "102": "400310331222424255355154430400442435220251010300444411",
        "114": "3432220243",
        "7": "22413",
        "43": "513433334535312"
      },
      "StartRoom": 7,
      "Level": 7,
      "EntryDoor": 0
    }
  },
  {
    "Id": "a92fd71c77a443c58727fb9a2d207004",
    "Name": "Super 4",
    "Maze": {
      "Stars": [
        "94",
        "34",
        "64",
        "2"
      ],
      "Path": "4430312124400343340110440443311044455152244043",
      "Traps": {
        "93": "4043000251515554334040103400044524432",
        "76": "55152544302033355300120212234435550"
      },
      "StartRoom": 127,
      "Level": 7,
      "EntryDoor": 2
    }
  },
  {
    "Id": "a92fd71c77a443c58727fb9a2d207005",
    "Name": "Super 5",
    "Maze": {
      "Stars": [
        "82",
        "39",
        "99",
        "58"
      ],
      "Path": "01511102033120030355304354401311130355300",
      "Traps": {
        "114": "430221450",
        "8": "51154451111514535224453040350",
        "98": "2503",
        "44": "12254544040453425112254032",
        "97": "2503"
      },
      "StartRoom": 122,
      "Level": 7,
      "EntryDoor": 2
    }
  },
  {
    "Id": "a92fd71c77a443c58727fb9a2d207006",
    "Name": "Super 6",
    "Maze": {
      "Stars": [
        "116",
        "70",
        "11",
        "75"
      ],
      "Path": "21511025425353043440435252554530020303",
      "Traps": {
        "49": "120155545301345441224212423",
        "116": "23",
        "11": "34215245551",
        "110": "533535352511021130431113354000411520155555451"
      },
      "StartRoom": 4,
      "Level": 7,
      "EntryDoor": 3
    }
  },
  {
    "Id": "a92fd71c77a443c58727fb9a2d207007",
    "Name": "Super 7",
    "Maze": {
      "Stars": [
        "31",
        "40",
        "78",
        "95"
      ],
      "Path": "53455102121221202551015555403334242434340401012025112110310",
      "Traps": {
        "63": "2430203",
        "47": "03111504",
        "70": "41",
        "85": "4334222102052422432",
        "113": "32",
        "32": "53102133344215443134501"
      },
      "StartRoom": 3,
      "Level": 7,
      "EntryDoor": 3
    }
  },
  {
    "Id": "a92fd71c77a443c58727fb9a2d207008",
    "Name": "Super 8",
    "Maze": {
      "Stars": [
        "97",
        "41",
        "101",
        "7"
      ],
      "Path": "5112245451111131013110353424354251004344000",
      "Traps": {
        "86": "32",
        "94": "013221554210131111154244441",
        "55": "2032124525442001",
        "35": "1535515205212421",
        "69": "25440345155443110411",
        "48": "0325",
        "6": "154044511500"
      },
      "StartRoom": 16,
      "Level": 7,
      "EntryDoor": 4
    }
  },
  {
    "Id": "a92fd71c77a443c58727fb9a2d207009",
    "Name": "Super 9",
    "Maze": {
      "Stars": [
        "50",
        "109",
        "43",
        "10"
      ],
      "Path": "021302211034421100034543353000301510220",
      "Traps": {
        "1": "2451101202334442",
        "39": "404534225552212531023004335242150",
        "45": "53404522421254434551043030354223"
      },
      "StartRoom": 122,
      "Level": 7,
      "EntryDoor": 5
    }
  },
  {
    "Id": "a92fd71c77a443c58727fb9a2d208001",
    "Name": "Extreme 1",
    "Maze": {
      "Stars": [
        "10",
        "153",
        "76",
        "96",
        "87"
      ],
      "Path": "255110211131203013020201225335553422422002551011",
      "Traps": {
        "125": "4015102521520153010030353043011555",
        "118": "1504",
        "45": "03543553552435031302030125353",
        "143": "32",
        "82": "135500",
        "51": "552220221022211544343521301113452",
        "44": "41"
      },
      "StartRoom": 51,
      "Level": 8,
      "EntryDoor": 4
    }
  },
  {
    "Id": "a92fd71c77a443c58727fb9a2d208002",
    "Name": "Extreme 2",
    "Maze": {
      "Stars": [
        "91",
        "23",
        "41",
        "110",
        "129"
      ],
      "Path": "12130301112244542102110302033400133104330220",
      "Traps": {
        "131": "000342552503",
        "140": "0325",
        "33": "520112033543002510023453",
        "54": "33110312554554045452152001522031000220101554244351503",
        "145": "423404040",
        "159": "1504"
      },
      "StartRoom": 153,
      "Level": 8,
      "EntryDoor": 5
    }
  },
  {
    "Id": "a92fd71c77a443c58727fb9a2d208003",
    "Name": "Extreme 3",
    "Maze": {
      "Stars": [
        "77",
        "82",
        "33",
        "75",
        "138"
      ],
      "Path": "2131215124221254253340353003424334045342224524522244354",
      "Traps": {
        "150": "34444552002021022003340433352224433304002111310122214",
        "169": "00004533312143",
        "122": "44212031003030103425325"
      },
      "StartRoom": 5,
      "Level": 8,
      "EntryDoor": 3
    }
  },
  {
    "Id": "a92fd71c77a443c58727fb9a2d208004",
    "Name": "Extreme 4",
    "Maze": {
      "Stars": [
        "120",
        "83",
        "106",
        "125",
        "142"
      ],
      "Path": "3310345133431040111040331312012155353422111310000",
      "Traps": {
        "87": "11112445343311110353034044044220401",
        "80": "2503",
        "69": "042443221102555331121211255100004544",
        "73": "04442222125425535444400401201312244244433510",
        "81": "3412"
      },
      "StartRoom": 153,
      "Level": 8,
      "EntryDoor": 5
    }
  },
  {
    "Id": "a92fd71c77a443c58727fb9a2d208005",
    "Name": "Extreme 5",
    "Maze": {
      "Stars": [
        "146",
        "39",
        "160",
        "90",
        "120"
      ],
      "Path": "3440455355120202200342003344424403013134425353400",
      "Traps": {
        "167": "443445114",
        "161": "420302034530555543423",
        "41": "131155215213020023",
        "19": "5535245205",
        "79": "5101021551255453331302251001121553405"
      },
      "StartRoom": 92,
      "Level": 8,
      "EntryDoor": 2
    }
  },
  {
    "Id": "a92fd71c77a443c58727fb9a2d208006",
    "Name": "Extreme 6",
    "Maze": {
      "Stars": [
        "32",
        "159",
        "66",
        "25",
        "84"
      ],
      "Path": "34440401020015511220303040113331340343554251001552244044534043012401300",
      "Traps": {
        "160": "420344425443530403533331040021300040120112020",
        "54": "51055554031332",
        "86": "3412",
        "119": "0325",
        "98": "31542154352233",
        "142": "030423"
      },
      "StartRoom": 167,
      "Level": 8,
      "EntryDoor": 5
    }
  },
  {
    "Id": "a92fd71c77a443c58727fb9a2d208007",
    "Name": "Extreme 7",
    "Maze": {
      "Stars": [
        "102",
        "7",
        "108",
        "138",
        "40"
      ],
      "Path": "553551545244313104345443352535333311111130200100100",
      "Traps": {
        "109": "4202512103020110435531352",
        "8": "253523304441",
        "161": "32",
        "9": "255355212444001113010400454521215551001023031344225315",
        "146": "5200200240"
      },
      "StartRoom": 106,
      "Level": 8,
      "EntryDoor": 2
    }
  },
  {
    "Id": "a92fd71c77a443c58727fb9a2d208008",
    "Name": "Extreme 8",
    "Maze": {
      "Stars": [
        "112",
        "76",
        "64",
        "45",
        "144"
      ],
      "Path": "120130000045530011112022453353552113452212004002012540252243521221",
      "Traps": {
        "83": "315225202000435355355251035453333112532",
        "106": "431340033433124502",
        "165": "33554040",
        "39": "55103022225520"
      },
      "StartRoom": 78,
      "Level": 8,
      "EntryDoor": 5
    }
  },
  {
    "Id": "a92fd71c77a443c58727fb9a2d208009",
    "Name": "Extreme 9",
    "Maze": {
      "Stars": [
        "72",
        "115",
        "110",
        "4",
        "49"
      ],
      "Path": "02001331220312245222534545122201130151253542252",
      "Traps": {
        "26": "4354121033122552220022553033302",
        "34": "3223",
        "45": "3502",
        "150": "2544444301335431043045533011311200431014",
        "88": "335211512515455412005"
      },
      "StartRoom": 39,
      "Level": 8,
      "EntryDoor": 3
    }
  },
  {
    "Id": "a92fd71c77a443c58727fb9a2d209001",
    "Name": "Awful 1",
    "Maze": {
      "Stars": [
        "104",
        "47",
        "163",
        "197",
        "55"
      ],
      "Path": "13112154425124540403134524245252211213343111311301253031103030",
      "Traps": {
        "29": "035550114",
        "111": "25102100130453313022454243401301544334245345",
        "189": "00443533330210110150",
        "113": "2044444515215253342254540040032225210102120301553"
      },
      "StartRoom": 10,
      "Level": 9,
      "EntryDoor": 4
    }
  },
  {
    "Id": "a92fd71c77a443c58727fb9a2d209002",
    "Name": "Awful 2",
    "Maze": {
      "Stars": [
        "1",
        "141",
        "97",
        "156",
        "76"
      ],
      "Path": "133120203401101001552534244215254442151100201001221",
      "Traps": {
        "99": "3125431125453455453535215030",
        "54": "5245425332",
        "143": "10013533043515202",
        "77": "531023043113301512422130043153",
        "26": "44422433543001555545115451554210100310252423"
      },
      "StartRoom": 176,
      "Level": 9,
      "EntryDoor": 5
    }
  },
  {
    "Id": "a92fd71c77a443c58727fb9a2d209003",
    "Name": "Awful 3",
    "Maze": {
      "Stars": [
        "108",
        "104",
        "84",
        "154",
        "23"
      ],
      "Path": "131202003353521100431343430004434033422551255355431043102121015542454001343533040301225335452433",
      "Traps": {
        "151": "134221255400453330034530103521152212202242535511020313100354310415",
        "54": "4302151224220254525005"
      },
      "StartRoom": 214,
      "Level": 9,
      "EntryDoor": 5
    }
  },
  {
    "Id": "a92fd71c77a443c58727fb9a2d209004",
    "Name": "Awful 4",
    "Maze": {
      "Stars": [
        "94",
        "29",
        "179",
        "162",
        "125"
      ],
      "Path": "151202515100020312025455112001304043433121313103545440130454553545333",
      "Traps": {
        "125": "35304551222",
        "30": "24044044045243045553004535251242343021",
        "69": "243134202",
        "198": "3104331202034430210434033442431010",
        "123": "52533303552503",
        "201": "3223",
        "197": "3223"
      },
      "StartRoom": 134,
      "Level": 9,
      "EntryDoor": 4
    }
  },
  {
    "Id": "a92fd71c77a443c58727fb9a2d209005",
    "Name": "Awful 5",
    "Maze": {
      "Stars": [
        "125",
        "170",
        "75",
        "196",
        "134"
      ],
      "Path": "543535354045515124535242243522131022245215115211030444313303310252025511540011511300302100",
      "Traps": {
        "184": "1311254545411105",
        "140": "14",
        "101": "22215222213121444",
        "171": "224501",
        "60": "1545400103312151515120333012421225352154404341"
      },
      "StartRoom": 7,
      "Level": 9,
      "EntryDoor": 0
    }
  },
  {
    "Id": "a92fd71c77a443c58727fb9a2d209006",
    "Name": "Awful 6",
    "Maze": {
      "Stars": [
        "73",
        "133",
        "93",
        "80",
        "150"
      ],
      "Path": "155352155511312210213104003130110302224555425352245221302202553543403355515422",
      "Traps": {
        "84": "224242",
        "163": "042222033133443300252252",
        "22": "21022001133114",
        "61": "540440111515553435122225555514",
        "204": "2053",
        "129": "52020113434424000203013251525340"
      },
      "StartRoom": 31,
      "Level": 9,
      "EntryDoor": 4
    }
  },
  {
    "Id": "a92fd71c77a443c58727fb9a2d209007",
    "Name": "Awful 7",
    "Maze": {
      "Stars": [
        "64",
        "112",
        "153",
        "35",
        "192"
      ],
      "Path": "1154215122252020100045534244333301152001012451101044310151120200200",
      "Traps": {
        "66": "153345355442433352422435033",
        "16": "5555443133345124425424245230",
        "148": "344543024542120254252433451544411",
        "154": "534012112154214",
        "7": "545542532"
      },
      "StartRoom": 101,
      "Level": 9,
      "EntryDoor": 4
    }
  },
  {
    "Id": "a92fd71c77a443c58727fb9a2d209008",
    "Name": "Awful 8",
    "Maze": {
      "Stars": [
        "166",
        "63",
        "38",
        "83",
        "101"
      ],
      "Path": "10313020344342243434004004034303110202524342403044543",
      "Traps": {
        "46": "4004554552244222000020301200112534221524244",
        "66": "25252130031022421544043031035340345155213155425155030",
        "190": "1101515510131044343534014434552422131015132"
      },
      "StartRoom": 216,
      "Level": 9,
      "EntryDoor": 2
    }
  },
  {
    "Id": "a92fd71c77a443c58727fb9a2d209009",
    "Name": "Awful 9",
    "Maze": {
      "Stars": [
        "217",
        "189",
        "147",
        "112",
        "15"
      ],
      "Path": "0115454555224511553125100002115554004552421242111004012522",
      "Traps": {
        "206": "15304111550",
        "94": "1545112110013354304543001511212225424242445404450002110331345202",
        "77": "240003404310212424554045244435222532",
      },
      "StartRoom": 20,
      "Level": 9,
      "EntryDoor": 3
    }
  },
  {
    "Id": "a92fd71c77a443c58727fb9a2d20a001",
    "Name": "Crazy 1",
    "Maze": {
      "Stars": [
        "230",
        "56",
        "24",
        "108",
        "221"
      ],
      "Path": "51201311110134353354245110211221012242201333303404035543535300",
      "Traps": {
        "217": "034515442421010200312512242453424404424333310434331202200403544040550",
        "236": "333352222242100000043355400333",
        "56": "4425542221134310452",
        "145": "5331344352122243303031340404422253502"
      },
      "StartRoom": 76,
      "Level": 10,
      "EntryDoor": 3
    }
  },
  {
    "Id": "a92fd71c77a443c58727fb9a2d20a002",
    "Name": "Crazy 2",
    "Maze": {
      "Stars": [
        "142",
        "171",
        "55",
        "160",
        "63"
      ],
      "Path": "13454353433553342224333301133033120043003553401040012243100",
      "Traps": {
        "80": "021330012542201211511301335330151222542251255515454043313000453354344412255220121333540011520121035344240",
        "153": "455124544501",
        "28": "204311311552452113422",
        "264": "0415"
      },
      "StartRoom": 270,
      "Level": 10,
      "EntryDoor": 5
    }
  },
  {
    "Id": "a92fd71c77a443c58727fb9a2d20a003",
    "Name": "Crazy 3",
    "Maze": {
      "Stars": [
        "88",
        "164",
        "201",
        "170",
        "30"
      ],
      "Path": "44551020301310354003343310104453344311112003440445213344530",
      "Traps": {
        "202": "35102524212202003000345255533131333530113133311242225120255242445111",
        "148": "45201102000252455354225333011333021334012203011553343544000201001445405"
      },
      "StartRoom": 250,
      "Level": 10,
      "EntryDoor": 2
    }
  },
  {
    "Id": "a92fd71c77a443c58727fb9a2d20a004",
    "Name": "Crazy 4",
    "Maze": {
      "Stars": [
        "33",
        "144",
        "115",
        "166",
        "86"
      ],
      "Path": "44424211310034244454224344300101121033540313103431343113134540443553524515543033",
      "Traps": {
        "209": "3010113134543355511301013453442544424335545530311304511034013122243541",
        "9": "12452412511331341",
        "76": "515151545115421515100310211544515514553004532"
      },
      "StartRoom": 250,
      "Level": 10,
      "EntryDoor": 1
    }
  },
  {
    "Id": "a92fd71c77a443c58727fb9a2d20a005",
    "Name": "Crazy 5",
    "Maze": {
      "Stars": [
        "91",
        "172",
        "123",
        "23",
        "165"
      ],
      "Path": "44422434355301115525403545535551511222025422202220300302113002215452434515245152",
      "Traps": {
        "138": "023310",
        "159": "13044302111525310155515543542125342440424125110432",
        "71": "00112442202133513",
        "95": "4501",
        "109": "51112455215202151055432",
        "200": "1013104400210130020300021334555343132105"
      },
      "StartRoom": 7,
      "Level": 10,
      "EntryDoor": 3
    }
  },
  {
    "Id": "a92fd71c77a443c58727fb9a2d20a006",
    "Name": "Crazy 6",
    "Maze": {
      "Stars": [
        "146",
        "176",
        "122",
        "53",
        "49"
      ],
      "Path": "3400220251000104303435255534535433010221043113434303433121302133120330",
      "Traps": {
        "10": "54243045434451545110043453551524254313010",
        "42": "555421200033122524215453022303",
        "21": "22440034250",
        "137": "3355454",
        "179": "2540003342453504",
        "109": "251102251544040100124225145553032",
        "161": "4501",
        "266": "444353001515112113"
      },
      "StartRoom": 268,
      "Level": 10,
      "EntryDoor": 2
    }
  },
  {
    "Id": "a92fd71c77a443c58727fb9a2d20a007",
    "Name": "Crazy 7",
    "Maze": {
      "Stars": [
        "183",
        "144",
        "41",
        "62",
        "174"
      ],
      "Path": "455154522534430133424245124433134455210221252435345213542",
      "Traps": {
        "200": "431033044555124212521154211",
        "81": "215212001500445403445530031130220031104445354345152524553302003514",
        "151": "<03434></03434>",
        "37": "31512",
        "163": "3134525510005",
        "234": "0421012155345353434404424453",
        "67": "531100225405"
      },
      "StartRoom": 108,
      "Level": 10,
      "EntryDoor": 0
    }
  },
  {
    "Id": "a92fd71c77a443c58727fb9a2d20a008",
    "Name": "Crazy 8",
    "Maze": {
      "Stars": [
        "41",
        "240",
        "144",
        "208",
        "147"
      ],
      "Path": "155111311040102254545111203452252011222030400203453311103300",
      "Traps": {
        "203": "35124440335403455152215152105",
        "29": "311254404345331111111525515150",
        "111": "4355202002121033424343000121300354242503",
        "123": "112",
        "179": "0454001115555453540522025540",
        "266": "012021040353354553354521021114"
      },
      "StartRoom": 47,
      "Level": 10,
      "EntryDoor": 4
    }
  },
  {
    "Id": "a92fd71c77a443c58727fb9a2d20a009",
    "Name": "Crazy 9",
    "Maze": {
      "Stars": [
        "49",
        "92",
        "240",
        "207",
        "107"
      ],
      "Path": "30452433020134313442421530151201304311124522511331300403113001300100",
      "Traps": {
        "148": "15103334421543521242103040",
        "122": "01003445201521154534512524421115544215543352430313350112114",
        "86": "4444222",
        "50": "335530013112253352511524534530132",
        "4": "11213122020233442",
        "254": "12020322",
        "150": "112",
        "175": "1044000321035",
        "103": "5500"
      },
      "StartRoom": 264,
      "Level": 10,
      "EntryDoor": 2
    }
  },
  {
    "Id": "a92fd71c77a443c58727fb9a2d20b001",
    "Name": "Martian 1",
    "Maze": {
      "Stars": [
        "3",
        "90",
        "189",
        "317",
        "234"
      ],
      "Path": "424454310115245525335530035552225530354535242121554515200000152243551221043102212252",
      "Traps": {
        "28": "430225424222030000233423",
        "65": "535215125352454335244033021302104004011222225202545244451253540342421250120003133401022444",
        "178": "3302254215200301255152144405",
        "316": "10452435345353534300220542514",
        "105": "5",
        "160": "1",
        "206": "01"
      },
      "StartRoom": 11,
      "Level": 11,
      "EntryDoor": 1
    }
  },
  {
    "Id": "a92fd71c77a443c58727fb9a2d20b002",
    "Name": "Martian 2",
    "Maze": {
      "Stars": [
        "106",
        "82",
        "260",
        "185",
        "176"
      ],
      "Path": "42452430442243353044224554000225253542215540334001530210102242200021312512243442512115224453552211334252201100340131010211",
      "Traps": {
        "330": "103002545432514",
        "265": "0253400113250",
        "7": "4501",
        "195": "104530043352243403300125424425244434430152",
        "172": "5230",
        "98": "32",
        "188": "445254313043353002212445520252202222543331220145",
        "160": "11"
      },
      "StartRoom": 9,
      "Level": 11,
      "EntryDoor": 0
    }
  },
  {
    "Id": "a92fd71c77a443c58727fb9a2d20b003",
    "Name": "Martian 3",
    "Maze": {
      "Stars": [
        "215",
        "18",
        "93",
        "298",
        "275"
      ],
      "Path": "2225342555512443043400212003335333522212452454220225102515534313343424242102035303400310443525154253444212534404554",
      "Traps": {
        "195": "0155335421255555544511334554030204432521214",
        "288": "452124435430344301122131313341",
        "162": "2133452435552333331022423",
        "7": "124404442421021201102252025113",
        "216": "2233",
        "45": "1",
        "212": "1"
      },
      "StartRoom": 65,
      "Level": 11,
      "EntryDoor": 0
    }
  },
  {
    "Id": "a92fd71c77a443c58727fb9a2d20b004",
    "Name": "Martian 4",
    "Maze": {
      "Stars": [
        "69",
        "79",
        "186",
        "309",
        "57"
      ],
      "Path": "151022553551201525424255533133554212445121021025544012200133035400020213111554221",
      "Traps": {
        "140": "11111111",
        "102": "551010035331000354452041",
        "329": "402130220000455335",
        "300": "5244304523",
        "222": "54535552002104011325524521",
        "95": "112033352452121135212555333335350",
        "90": "40155155333043013021331222523404541",
        "23": "5551003404501"
      },
      "StartRoom": 7,
      "Level": 11,
      "EntryDoor": 0
    }
  },
  {
    "Id": "a92fd71c77a443c58727fb9a2d20b005",
    "Name": "Martian 5",
    "Maze": {
      "Stars": [
        "205",
        "307",
        "96",
        "159",
        "331"
      ],
      "Path": "55534354515552213313021040433003401311333012422025521035331244524222434354425404004011000300444343444300",
      "Traps": {
        "214": "10041",
        "235": "340404311221",
        "261": "25234354532",
        "327": "11345403553403444011313333425530331113354444001210102510010151022254044311555552214554003342214",
        "195": "4501",
        "44": "55"
      },
      "StartRoom": 215,
      "Level": 11,
      "EntryDoor": 1
    }
  },
  {
    "Id": "a92fd71c77a443c58727fb9a2d20b006",
    "Name": "Martian 6",
    "Maze": {
      "Stars": [
        "107",
        "260",
        "247",
        "170",
        "56"
      ],
      "Path": "34545440454034334424511520254403452224224330455521151225342244",
      "Traps": {
        "131": "44010200401225512152435515545355421124520440452113",
        "227": "30113310222435542253404443033533021313110151131000334254444011134444243452225201132",
        "257": "451102110443453403534331200403311545313",
        "180": "11"
      },
      "StartRoom": 50,
      "Level": 11,
      "EntryDoor": 1
    }
  },
  {
    "Id": "a92fd71c77a443c58727fb9a2d20b007",
    "Name": "Martian 7",
    "Maze": {
      "Stars": [
        "167",
        "277",
        "236",
        "82",
        "155"
      ],
      "Path": "1521302113043130444515213011001033004401020112212452440431043555152130225545400100454433443134353425155535301333",
      "Traps": {
        "286": "11",
        "154": "1334034442152",
        "303": "5331000100411",
        "114": "5005",
        "231": "124344520255524210031310430335401121334012151043344124",
        "276": "015155404031",
        "315": "540445354023",
        "58": "55",
        "17": "512101245444353342553530035552452032"
      },
      "StartRoom": 282,
      "Level": 11,
      "EntryDoor": 4
    }
  },
  {
    "Id": "a92fd71c77a443c58727fb9a2d20b008",
    "Name": "Martian 8",
    "Maze": {
      "Stars": [
        "285",
        "116",
        "101",
        "104",
        "242"
      ],
      "Path": "545202202551201242444242540345553425433033552421545530030445544",
      "Traps": {
        "278": "30044043342515154205",
        "294": "00013020354210",
        "144": "30442212500334",
        "208": "03303331335522253334401040401131311242422115421222210002545",
        "98": "3404343002241",
        "184": "110",
        "119": "0002224445424421113015111242444445312242220131351"
      },
      "StartRoom": 50,
      "Level": 11,
      "EntryDoor": 0
    }
  },
  {
    "Id": "a92fd71c77a443c58727fb9a2d20b009",
    "Name": "Martian 9",
    "Maze": {
      "Stars": [
        "223",
        "217",
        "308",
        "303",
        "131"
      ],
      "Path": "2515424300222220125243422202521213115110203404301035301031343344343440104343",
      "Traps": {
        "74": "4243303401345534500125",
        "37": "240125",
        "81": "553344444",
        "217": "3522222221324",
        "188": "353422234440151",
        "130": "220301522031152424422203100340",
        "246": "302111",
        "288": "240430203312233",
        "294": "04512452034422404114",
        "170": "254525244345",
        "67": "511125200225545212442520224435"
      },
      "StartRoom": 99,
      "Level": 11,
      "EntryDoor": 3
    }
  }
]